[
  {
    "word": "dessert",
    "meanings": [
      {
        "type": "名詞",
        "meaning_en_US": "A course that concludes a meal, typically sweet.",
        "meaning_zh_TW": "甜點",
        "wrong_meaning_zh_TW": [
          "開胃菜",
          "主菜",
          "飲品"
        ],
        "examples": [
          {
            "sentence": "We had chocolate cake for [dessert].",
            "translation_zh_TW": "我們吃了巧克力蛋糕作為甜點。"
          },
          {
            "sentence": "She always saves room for [dessert].",
            "translation_zh_TW": "她總是留點空間吃甜點。"
          },
          {
            "sentence": "The [dessert] was a perfect end to the meal.",
            "translation_zh_TW": "這道甜點是這頓飯的完美結尾。"
          }
        ],
        "synonyms": [
          "sweet",
          "treat"
        ]
      }
    ],
    "confusion": [
      "desert",
      "desserts",
      "despaired",
      "desserter"
    ]
  },
  {
    "word": "property",
    "meanings": [
      {
        "type": "名詞",
        "meaning_en_US": "A thing or things belonging to someone; possessions collectively.",
        "meaning_zh_TW": "財產",
        "wrong_meaning_zh_TW": [
          "服務",
          "標準",
          "借貸"
        ],
        "examples": [
          {
            "sentence": "They invested in real [property] to build wealth.",
            "translation_zh_TW": "他們投資房地產來累積財富。"
          },
          {
            "sentence": "The law protects the right to [property].",
            "translation_zh_TW": "法律保護財產的權利。"
          },
          {
            "sentence": "She sold her [property] for a good price.",
            "translation_zh_TW": "她以好價錢賣掉了她的財產。"
          }
        ],
        "synonyms": [
          "asset",
          "belonging"
        ]
      }
    ],
    "confusion": [
      "properties",
      "proprietor",
      "prophecy",
      "proximity"
    ]
  },
  {
    "word": "beetle",
    "meanings": [
      {
        "type": "名詞",
        "meaning_en_US": "An insect characterized by a hardened forewings and a straight line down the middle.",
        "meaning_zh_TW": "甲蟲",
        "wrong_meaning_zh_TW": [
          "蝴蝶",
          "蚊子",
          "蟋蟀"
        ],
        "examples": [
          {
            "sentence": "She found a shiny [beetle] on the leaf.",
            "translation_zh_TW": "她在葉子上發現了一隻閃亮的甲蟲"
          },
          {
            "sentence": "The [beetle] is known for its ability to survive in harsh conditions.",
            "translation_zh_TW": "這隻甲蟲以在惡劣條件下生存而聞名"
          },
          {
            "sentence": "They collected different types of [beetles] for research.",
            "translation_zh_TW": "他們收集了不同種類的甲蟲進行研究"
          }
        ],
        "synonyms": [
          "bug",
          "insect"
        ]
      }
    ],
    "confusion": [
      "beet",
      "beetling",
      "beatle",
      "beetled"
    ]
  },
  {
    "word": "organize",
    "meanings": [
      {
        "type": "動詞",
        "meaning_en_US": "To arrange systematically; to put in order.",
        "meaning_zh_TW": "整理",
        "wrong_meaning_zh_TW": [
          "懶惰",
          "隨意",
          "混亂"
        ],
        "examples": [
          {
            "sentence": "She plans to [organize] the event next month.",
            "translation_zh_TW": "她計畫下個月舉辦這次活動。"
          },
          {
            "sentence": "We need to [organize] our schedule properly.",
            "translation_zh_TW": "我們需要妥善安排我們的日程。"
          },
          {
            "sentence": "He can [organize] his files efficiently.",
            "translation_zh_TW": "他能有效地整理他的文件。"
          }
        ],
        "synonyms": [
          "arrange",
          "systematize"
        ]
      }
    ],
    "confusion": [
      "organic",
      "organism",
      "organized",
      "organizer"
    ]
  },
  {
    "word": "passion",
    "meanings": [
      {
        "type": "名詞",
        "meaning_en_US": "A strong feeling of enthusiasm or excitement for something or about doing something.",
        "meaning_zh_TW": "激情、熱情",
        "wrong_meaning_zh_TW": [
          "無聊",
          "冷漠",
          "煩惱"
        ],
        "examples": [
          {
            "sentence": "Her [passion] for painting inspired her friends.",
            "translation_zh_TW": "她對繪畫的熱情激勵了她的朋友。"
          },
          {
            "sentence": "He spoke with [passion] about his favorite subject.",
            "translation_zh_TW": "他對自己最喜愛的主題充滿熱情地談論。"
          },
          {
            "sentence": "Following your [passion] can lead to a fulfilling life.",
            "translation_zh_TW": "追隨你的激情可以導致充實的生活。"
          }
        ],
        "synonyms": [
          "enthusiasm",
          "zeal"
        ]
      }
    ],
    "confusion": [
      "passiun",
      "passsion",
      "pation",
      "pashion"
    ]
  },
  {
    "word": "stove",
    "meanings": [
      {
        "type": "名詞",
        "meaning_en_US": "A kitchen appliance used for cooking food.",
        "meaning_zh_TW": "爐子",
        "wrong_meaning_zh_TW": [
          "沙發",
          "凳子",
          "冰箱"
        ],
        "examples": [
          {
            "sentence": "She turned on the [stove] to boil water.",
            "translation_zh_TW": "她打開爐子煮水。"
          },
          {
            "sentence": "Make sure the [stove] is off before leaving.",
            "translation_zh_TW": "離開前確保爐子關掉。"
          },
          {
            "sentence": "He cooked dinner on the [stove] last night.",
            "translation_zh_TW": "他昨晚在爐子上做晚餐。"
          }
        ],
        "synonyms": [
          "range",
          "cooktop"
        ]
      }
    ],
    "confusion": [
      "stone",
      "stovepipe",
      "dove",
      "stove-top"
    ]
  },
  {
    "word": "truthful",
    "meanings": [
      {
        "type": "形容詞",
        "meaning_en_US": "Honest and not containing any lies.",
        "meaning_zh_TW": "真實的",
        "wrong_meaning_zh_TW": [
          "虛假的",
          "欺騙的",
          "模糊的"
        ],
        "examples": [
          {
            "sentence": "She is always [truthful] in her statements.",
            "translation_zh_TW": "她在陳述中總是保持真實。"
          },
          {
            "sentence": "It's important to be [truthful] in journalism.",
            "translation_zh_TW": "在新聞界保持真實是很重要的。"
          },
          {
            "sentence": "A [truthful] friend is hard to find.",
            "translation_zh_TW": "一個真誠的朋友很難找。"
          }
        ],
        "synonyms": [
          "honest",
          "sincere"
        ]
      }
    ],
    "confusion": [
      "truth",
      "trucial",
      "treaty",
      "truffle"
    ]
  },
  {
    "word": "bull",
    "meanings": [
      {
        "type": "名詞",
        "meaning_en_US": "An adult male of certain large mammals, especially cattle.",
        "meaning_zh_TW": "公牛",
        "wrong_meaning_zh_TW": [
          "母牛",
          "小牛",
          "羊"
        ],
        "examples": [
          {
            "sentence": "The [bull] roamed freely in the pasture.",
            "translation_zh_TW": "公牛在牧場上自由漫遊。"
          },
          {
            "sentence": "They raised a strong [bull] for the competition.",
            "translation_zh_TW": "他們為比賽養了一隻強壯的公牛。"
          },
          {
            "sentence": "A [bull] is known for its strength and size.",
            "translation_zh_TW": "公牛因其力量和體型而聞名。"
          }
        ],
        "synonyms": [
          "ox",
          "beef"
        ]
      }
    ],
    "confusion": [
      "bowl",
      "ball",
      "bulls",
      "bule"
    ]
  },
  {
    "word": "restrict",
    "meanings": [
      {
        "type": "動詞",
        "meaning_en_US": "To limit the number, amount, or size of something.",
        "meaning_zh_TW": "限制性的",
        "wrong_meaning_zh_TW": [
          "開放的",
          "自由的",
          "平等的"
        ],
        "examples": [
          {
            "sentence": "The law aims to [restrict] smoking in public places.",
            "translation_zh_TW": "該法律的目的是限制公共場所吸煙。"
          },
          {
            "sentence": "You should [restrict] your screen time for better health.",
            "translation_zh_TW": "為了更好的健康，你應該限制你的屏幕時間。"
          },
          {
            "sentence": "They plan to [restrict] access to certain areas.",
            "translation_zh_TW": "他們計劃限制對某些區域的進入。"
          }
        ],
        "synonyms": [
          "limit",
          "control"
        ]
      },
      {
        "type": "形容詞",
        "meaning_en_US": "Serving to limit or confine.",
        "meaning_zh_TW": "限制性的",
        "wrong_meaning_zh_TW": [
          "開放的",
          "自由的",
          "平等的"
        ],
        "examples": [
          {
            "sentence": "The [restrictive] policies hinder innovation.",
            "translation_zh_TW": "那些限制性的政策妨礙了創新。"
          },
          {
            "sentence": "He finds the [restrictive] rules frustrating.",
            "translation_zh_TW": "他覺得那些限制性的規則令人沮喪。"
          },
          {
            "sentence": "Such [restrictive] measures are necessary.",
            "translation_zh_TW": "這種限制性的措施是必要的。"
          }
        ],
        "synonyms": [
          "confining",
          "binding"
        ]
      }
    ],
    "confusion": [
      "restricted",
      "retract",
      "restrictor",
      "restruct"
    ]
  },
  {
    "word": "tighten",
    "meanings": [
      {
        "type": "動詞",
        "meaning_en_US": "To make something tighter or more secure.",
        "meaning_zh_TW": "收緊",
        "wrong_meaning_zh_TW": [
          "放鬆",
          "放開",
          "縮小"
        ],
        "examples": [
          {
            "sentence": "You need to [tighten] the screws on the shelf.",
            "translation_zh_TW": "你需要收緊架子的螺絲。"
          },
          {
            "sentence": "Please [tighten] your grip on the rope.",
            "translation_zh_TW": "請緊握繩子。"
          },
          {
            "sentence": "The coach instructed them to [tighten] their plays.",
            "translation_zh_TW": "教練指示他們要收緊進攻策略。"
          }
        ],
        "synonyms": [
          "secure",
          "fasten"
        ]
      }
    ],
    "confusion": [
      "tightning",
      "tightin",
      "tightner",
      "tightning"
    ]
  },
  {
    "word": "vision",
    "meanings": [
      {
        "type": "名詞",
        "meaning_en_US": "The faculty or state of being able to see.",
        "meaning_zh_TW": "視力、視覺",
        "wrong_meaning_zh_TW": [
          "顏色",
          "光線",
          "陰影"
        ],
        "examples": [
          {
            "sentence": "Her [vision] was blurred after the long hours of work.",
            "translation_zh_TW": "經過長時間的工作，她的視力模糊了。"
          },
          {
            "sentence": "He has a clear [vision] of the future.",
            "translation_zh_TW": "他對未來有著清晰的視野。"
          },
          {
            "sentence": "The doctor recommended eye exercises to improve her [vision].",
            "translation_zh_TW": "醫生建議進行眼部運動以改善她的視力。"
          }
        ],
        "synonyms": [
          "sight",
          "eyesight"
        ]
      },
      {
        "type": "名詞",
        "meaning_en_US": "The ability to think about or plan the future with imagination or wisdom.",
        "meaning_zh_TW": "構想、視野",
        "wrong_meaning_zh_TW": [
          "計劃",
          "念頭",
          "目標"
        ],
        "examples": [
          {
            "sentence": "Great leaders possess a powerful [vision].",
            "translation_zh_TW": "偉大的領導者擁有強大的構想。"
          },
          {
            "sentence": "His [vision] for the community includes more green spaces.",
            "translation_zh_TW": "他對社區的構想包括更多的綠地。"
          },
          {
            "sentence": "She shared her [vision] during the conference.",
            "translation_zh_TW": "她在會議上分享了她的構想。"
          }
        ],
        "synonyms": [
          "foresight",
          "imagination"
        ]
      }
    ],
    "confusion": [
      "revision",
      "decision",
      "division",
      "vison"
    ]
  },
  {
    "word": "capable",
    "meanings": [
      {
        "type": "形容詞",
        "meaning_en_US": "Having the ability or qualities necessary to do something.",
        "meaning_zh_TW": "有能力的",
        "wrong_meaning_zh_TW": [
          "無能的",
          "愚蠢的",
          "無用的"
        ],
        "examples": [
          {
            "sentence": "She is a [capable] leader.",
            "translation_zh_TW": "她是一位有能力的領導者"
          },
          {
            "sentence": "The team is [capable] of winning the championship.",
            "translation_zh_TW": "這支隊伍有能力贏得冠軍"
          },
          {
            "sentence": "He proved to be [capable] of great things.",
            "translation_zh_TW": "他證明了自己能夠成就非凡的事"
          }
        ],
        "synonyms": [
          "competent",
          "able"
        ]
      }
    ],
    "confusion": [
      "capabl",
      "capabil",
      "capablee",
      "capaple"
    ]
  },
  {
    "word": "trader",
    "meanings": [
      {
        "type": "名詞",
        "meaning_en_US": "A person who buys and sells goods for a profit.",
        "meaning_zh_TW": "商人",
        "wrong_meaning_zh_TW": [
          "顧客",
          "製造商",
          "經理"
        ],
        "examples": [
          {
            "sentence": "The [trader] negotiated a fair price for the goods.",
            "translation_zh_TW": "商人為貨物談判了公平的價格。"
          },
          {
            "sentence": "A successful [trader] needs to understand the market.",
            "translation_zh_TW": "成功的商人需要了解市場。"
          },
          {
            "sentence": "He is a [trader] in rare antiques.",
            "translation_zh_TW": "他是一位珍稀古董的商人。"
          }
        ],
        "synonyms": [
          "merchant",
          "dealer"
        ]
      }
    ],
    "confusion": [
      "trader",
      "traitor",
      "trade",
      "traced"
    ]
  },
  {
    "word": "pave",
    "meanings": [
      {
        "type": "動詞",
        "meaning_en_US": "To cover a surface with a hard material, especially for roads or paths.",
        "meaning_zh_TW": "鋪路",
        "wrong_meaning_zh_TW": [
          "挖掘",
          "剷除",
          "建造"
        ],
        "examples": [
          {
            "sentence": "They plan to [pave] the driveway next week.",
            "translation_zh_TW": "他們計劃下週鋪設車道。"
          },
          {
            "sentence": "The city decided to [pave] the roads with new asphalt.",
            "translation_zh_TW": "市政府決定用新瀝青鋪設道路。"
          },
          {
            "sentence": "Let's [pave] the path to make it easier to walk.",
            "translation_zh_TW": "讓我們鋪設小徑，以便更容易行走。"
          }
        ],
        "synonyms": [
          "surface",
          "cover"
        ]
      }
    ],
    "confusion": [
      "pavee",
      "paver",
      "pavey",
      "pav"
    ]
  },
  {
    "word": "sake",
    "meanings": [
      {
        "type": "名詞",
        "meaning_en_US": "A Japanese alcoholic beverage made from fermented rice.",
        "meaning_zh_TW": "清酒",
        "wrong_meaning_zh_TW": [
          "果汁",
          "紅酒",
          "啤酒"
        ],
        "examples": [
          {
            "sentence": "He toasted with a glass of [sake].",
            "translation_zh_TW": "他舉起一杯清酒祝酒。"
          },
          {
            "sentence": "She enjoys drinking [sake] with sushi.",
            "translation_zh_TW": "她喜歡和壽司一起喝清酒。"
          },
          {
            "sentence": "The restaurant offered different types of [sake].",
            "translation_zh_TW": "這家餐廳提供各種不同類型的清酒。"
          }
        ],
        "synonyms": [
          "rice wine",
          "nihonshu"
        ]
      }
    ],
    "confusion": [
      "sake",
      "saki",
      "sakee",
      "sakewa"
    ]
  },
  {
    "word": "knit",
    "meanings": [
      {
        "type": "動詞",
        "meaning_en_US": "To make a piece of clothing or fabric by interlocking loops of yarn with needles.",
        "meaning_zh_TW": "編織",
        "wrong_meaning_zh_TW": [
          "打結",
          "釘釘子",
          "搭建"
        ],
        "examples": [
          {
            "sentence": "She learned to [knit] a sweater.",
            "translation_zh_TW": "她學會了編織一件毛衣。"
          },
          {
            "sentence": "They decided to [knit] scarves for the winter.",
            "translation_zh_TW": "他們決定為冬天編織圍巾。"
          },
          {
            "sentence": "He likes to [knit] in his free time.",
            "translation_zh_TW": "他喜歡在空閒時間編織。"
          }
        ],
        "synonyms": [
          "weave",
          "crochet"
        ]
      }
    ],
    "confusion": [
      "nit",
      "kit",
      "knight",
      "not"
    ]
  },
  {
    "word": "release",
    "meanings": [
      {
        "type": "動詞",
        "meaning_en_US": "To set free or allow to escape.",
        "meaning_zh_TW": "釋放",
        "wrong_meaning_zh_TW": [
          "束縛",
          "固守",
          "限制"
        ],
        "examples": [
          {
            "sentence": "The company will [release] the new product next month.",
            "translation_zh_TW": "該公司將於下個月釋放新產品"
          },
          {
            "sentence": "She felt a weight lifted when she [released] her fears.",
            "translation_zh_TW": "當她釋放了自己的恐懼時，感覺負擔減輕了"
          },
          {
            "sentence": "They decided to [release] the animals back into the wild.",
            "translation_zh_TW": "他們決定將動物釋放回野外"
          }
        ],
        "synonyms": [
          "liberate",
          "free"
        ]
      }
    ],
    "confusion": [
      "relese",
      "relieve",
      "releases",
      "relose"
    ]
  },
  {
    "word": "temperature",
    "meanings": [
      {
        "type": "名詞",
        "meaning_en_US": "A measure of the warmth or coldness of an object or substance with reference to a standard value.",
        "meaning_zh_TW": "溫度",
        "wrong_meaning_zh_TW": [
          "濕度",
          "氣壓",
          "風速"
        ],
        "examples": [
          {
            "sentence": "The doctor took her [temperature] to check for fever.",
            "translation_zh_TW": "醫生測量了她的溫度以檢查是否發燒。"
          },
          {
            "sentence": "The [temperature] dropped significantly overnight.",
            "translation_zh_TW": "夜間溫度顯著下降。"
          },
          {
            "sentence": "You should keep the [temperature] stable in the fridge.",
            "translation_zh_TW": "你應該保持冰箱內的溫度穩定。"
          }
        ],
        "synonyms": [
          "heat level",
          "climate"
        ]
      }
    ],
    "confusion": [
      "tempera",
      "template",
      "tempered",
      "tempest"
    ]
  },
  {
    "word": "stale",
    "meanings": [
      {
        "type": "形容詞",
        "meaning_en_US": "No longer fresh and pleasant to eat; hard, musty, or dry.",
        "meaning_zh_TW": "不新鮮的",
        "wrong_meaning_zh_TW": [
          "新鮮的",
          "香甜的",
          "柔軟的"
        ],
        "examples": [
          {
            "sentence": "The bread became [stale] after a week.",
            "translation_zh_TW": "這塊麵包一周後變得不新鮮了。"
          },
          {
            "sentence": "He found a [stale] sandwich in his bag.",
            "translation_zh_TW": "他在包裡找到了一個不新鮮的三明治。"
          },
          {
            "sentence": "The air in the room felt [stale].",
            "translation_zh_TW": "房間裡的空氣感覺不新鮮。"
          }
        ],
        "synonyms": [
          "old",
          "worn"
        ]
      }
    ],
    "confusion": [
      "scale",
      "tale",
      "stail",
      "stela"
    ]
  },
  {
    "word": "pause",
    "meanings": [
      {
        "type": "動詞",
        "meaning_en_US": "To temporarily stop or halt; to take a break.",
        "meaning_zh_TW": "暫停",
        "wrong_meaning_zh_TW": [
          "進行",
          "完成",
          "開始"
        ],
        "examples": [
          {
            "sentence": "Please [pause] the video for a moment.",
            "translation_zh_TW": "請暫停視頻片刻。"
          },
          {
            "sentence": "He has to [pause] to think before answering.",
            "translation_zh_TW": "他必須暫停一下考慮後再回答。"
          },
          {
            "sentence": "We should [pause] here to catch our breath.",
            "translation_zh_TW": "我們應該在這裡暫停一下，喘口氣。"
          }
        ],
        "synonyms": [
          "stop",
          "halt"
        ]
      }
    ],
    "confusion": [
      "pouse",
      "pase",
      "paws",
      "pase"
    ]
  }
]